magnetodb/__init__.py
magnetodb/policy.py
magnetodb/context.py
magnetodb/version.py
magnetodb/i18n.py
magnetodb/openstack/__init__.py
magnetodb/openstack/common/__init__.py
magnetodb/openstack/common/systemd.py
magnetodb/openstack/common/eventlet_backdoor.py
magnetodb/openstack/common/policy.py
magnetodb/openstack/common/local.py
magnetodb/openstack/common/importutils.py
magnetodb/openstack/common/service.py
magnetodb/openstack/common/uuidutils.py
magnetodb/openstack/common/_i18n.py
magnetodb/openstack/common/threadgroup.py
magnetodb/openstack/common/log.py
magnetodb/openstack/common/exception.py
magnetodb/openstack/common/loopingcall.py
magnetodb/openstack/common/strutils.py
magnetodb/storage/__init__.py
magnetodb/storage/models.py
magnetodb/storage/restore_info_repo/__init__.py
magnetodb/storage/restore_info_repo/cassandra_impl.py
magnetodb/storage/table_info_repo/__init__.py
magnetodb/storage/table_info_repo/cassandra_impl.py
magnetodb/storage/manager/__init__.py
magnetodb/storage/manager/queued_impl.py
magnetodb/storage/manager/simple_impl.py
magnetodb/storage/manager/async_simple_impl.py
magnetodb/storage/backup_info_repo/__init__.py
magnetodb/storage/backup_info_repo/cassandra_impl.py
magnetodb/storage/restore_manager/__init__.py
magnetodb/storage/driver/__init__.py
magnetodb/storage/driver/cassandra/__init__.py
magnetodb/storage/driver/cassandra/cassandra_impl.py
magnetodb/storage/driver/cassandra/cassandra_with_custom_lsi_impl.py
magnetodb/storage/driver/cassandra/encoder.py
magnetodb/storage/backup_manager/__init__.py
magnetodb/tests/__init__.py
magnetodb/tests/storage/__init__.py
magnetodb/tests/storage/test_cassandra_with_custom_lsi_impl.py
magnetodb/tests/storage/test_cassandra_impl.py
magnetodb/tests/fake/__init__.py
magnetodb/tests/fake/magnetodb_api_fake.py
magnetodb/tests/unittests/__init__.py
magnetodb/tests/unittests/storage/__init__.py
magnetodb/tests/unittests/storage/test_model.py
magnetodb-2015.1.dist-info/DESCRIPTION.rst
magnetodb-2015.1.dist-info/METADATA
magnetodb-2015.1.dist-info/WHEEL
magnetodb-2015.1.dist-info/top_level.txt
magnetodb-2015.1.dist-info/pbr.json
magnetodb-2015.1.dist-info/metadata.json
magnetodb-2015.1.dist-info/RECORD
