Metadata-Version: 2.0
Name: magnetodb
Version: 2015.1
Summary: MagnetoDB is key-value database service for OpenStack cloud
Home-page: http://www.openstack.org/
Author: OpenStack
Author-email: openstack-dev@lists.openstack.org
License: UNKNOWN
Platform: UNKNOWN
Classifier: Environment :: OpenStack
Classifier: Intended Audience :: Information Technology
Classifier: Intended Audience :: System Administrators
Classifier: License :: OSI Approved :: Apache Software License
Classifier: Operating System :: POSIX :: Linux
Classifier: Programming Language :: Python
Classifier: Programming Language :: Python :: 2
Classifier: Programming Language :: Python :: 2.7
Requires-Dist: blist
Requires-Dist: cassandra-driver (==2.1.3)
Requires-Dist: eventlet (>=0.15.2)
Requires-Dist: gunicorn (>=18.0)
Requires-Dist: iso8601 (>=0.1.9)
Requires-Dist: jsonschema (>=2.0.0,<3.0.0)
Requires-Dist: keystonemiddleware (>=1.0.0)
Requires-Dist: kombu (>=2.5.0)
Requires-Dist: oslo.config (>=1.4.0)
Requires-Dist: oslo.context (>=0.1.0)
Requires-Dist: oslo.i18n (>=1.3.0)
Requires-Dist: oslo.messaging (<1.9.0,>=1.8.0)
Requires-Dist: oslo.serialization (>=1.2.0)
Requires-Dist: oslo.utils (>=1.2.0)
Requires-Dist: pecan (>=0.8.0)
Requires-Dist: pbr (>=0.6,!=0.7,<1.0)
Requires-Dist: pyjolokia
Requires-Dist: python-keystoneclient (>=0.11.1)
Requires-Dist: six (>=1.7.0)
Requires-Dist: Babel (>=1.3)
Requires-Dist: Paste
Requires-Dist: PasteDeploy (>=1.5.0)
Requires-Dist: WebOb (>=1.2.3)
